edc_test_settings/__init__.py
edc_test_settings/apps.py
edc_test_settings/default_installed_apps.py
edc_test_settings/default_test_settings.py
edc_test_settings/func_main.py
edc_test_settings/tests/__init__.py
edc_test_settings/tests/models.py
edc_test_settings/tests/tests.py
edc_test_settings/tests/urls.py
edc_test_settings-2.0.0.dist-info/licenses/LICENSE
edc_test_settings-2.0.0.dist-info/WHEEL
edc_test_settings-2.0.0.dist-info/METADATA
edc_test_settings-2.0.0.dist-info/RECORD
